echoss_storage/__init__.py
echoss_storage/s3_handler.py
echoss_storage-1.2.0.dist-info/METADATA
echoss_storage-1.2.0.dist-info/WHEEL
echoss_storage-1.2.0.dist-info/top_level.txt
echoss_storage-1.2.0.dist-info/RECORD
