Metadata-Version: 2.4
Name: echoss-storage
Version: 1.2.0
Summary: echoss AI Bigdata Solution - Object Storage like S3 handler
Home-page: 
Author: ckkim
Author-email: ckkim@12cm.co.kr
Keywords: echoss,object storage,s3handler,s3_handler
Requires-Python: >3.7
Requires-Dist: boto3<2.0,>=1.19.0
Requires-Dist: opencv-python~=4.8.0.74
Requires-Dist: numpy>=1.22.3
Requires-Dist: tqdm>=4.63.2
Requires-Dist: pillow~=10.1.0
Requires-Dist: echoss-fileformat>=1.1.0
Dynamic: author
Dynamic: author-email
Dynamic: description
Dynamic: description-content-type
Dynamic: keywords
Dynamic: requires-dist
Dynamic: requires-python
Dynamic: summary
